qlasskit/__init__.py
qlasskit/boolquant.py
qlasskit/bqm.py
qlasskit/qlassfun.py
qlasskit/algorithms/__init__.py
qlasskit/algorithms/bernsteinvazirani.py
qlasskit/algorithms/counting.py
qlasskit/algorithms/deutschjozsa.py
qlasskit/algorithms/grover.py
qlasskit/algorithms/qalgorithm.py
qlasskit/algorithms/simon.py
qlasskit/ast2ast/__init__.py
qlasskit/ast2ast/ast2ast.py
qlasskit/ast2ast/astrewriter.py
qlasskit/ast2ast/constantfolder.py
qlasskit/ast2ast/env.py
qlasskit/ast2ast/replacemultitargetassign.py
qlasskit/ast2ast/replacetypeann.py
qlasskit/ast2logic/__init__.py
qlasskit/ast2logic/env.py
qlasskit/ast2logic/exceptions.py
qlasskit/ast2logic/t_arguments.py
qlasskit/ast2logic/t_ast.py
qlasskit/ast2logic/t_expression.py
qlasskit/ast2logic/t_statement.py
qlasskit/ast2logic/typing.py
qlasskit/ast2logic/utils.py
qlasskit/boolopt/__init__.py
qlasskit/boolopt/bool_optimizer.py
qlasskit/boolopt/exp_transformers.py
qlasskit/boolopt/sympytransformer.py
qlasskit/compiler/__init__.py
qlasskit/compiler/compiler.py
qlasskit/compiler/expqmap.py
qlasskit/compiler/internalcompiler.py
qlasskit/compiler/recompiler.py
qlasskit/compiler/tweedledumcompiler.py
qlasskit/decompiler/__init__.py
qlasskit/decompiler/decompiler.py
qlasskit/decompiler/decopt.py
qlasskit/qcircuit/__init__.py
qlasskit/qcircuit/cnotsim.py
qlasskit/qcircuit/exporter.py
qlasskit/qcircuit/exporter_cirq.py
qlasskit/qcircuit/exporter_pennylane.py
qlasskit/qcircuit/exporter_qasm.py
qlasskit/qcircuit/exporter_qiskit.py
qlasskit/qcircuit/exporter_qutip.py
qlasskit/qcircuit/exporter_sympy.py
qlasskit/qcircuit/gates.py
qlasskit/qcircuit/qcircuit.py
qlasskit/qcircuit/qcircuitenhanced.py
qlasskit/qcircuit/qcircuitwrapper.py
qlasskit/tools/__init__.py
qlasskit/tools/py2bexp.py
qlasskit/tools/py2qasm.py
qlasskit/tools/tools.py
qlasskit/tools/utils.py
qlasskit/types/__init__.py
qlasskit/types/parameter.py
qlasskit/types/qbool.py
qlasskit/types/qchar.py
qlasskit/types/qfixed.py
qlasskit/types/qint.py
qlasskit/types/qlist.py
qlasskit-0.1.38.dist-info/licenses/LICENSE
qlasskit-0.1.38.dist-info/METADATA
qlasskit-0.1.38.dist-info/WHEEL
qlasskit-0.1.38.dist-info/entry_points.txt
qlasskit-0.1.38.dist-info/top_level.txt
qlasskit-0.1.38.dist-info/RECORD
