Metadata-Version: 2.4
Name: qlasskit
Version: 0.1.38
Summary: A python-to-quantum compiler
Author-email: Davide Gessa <gessadavide@gmail.com>
License: Apache 2.0
Project-URL: Homepage, https://github.com/dakk/qlasskit
Project-URL: Bug Tracker, https://github.com/dakk/qlasskit/issues/
Project-URL: Documentation, https://dakk.github.io/qlasskit
Project-URL: Source, https://github.com/dakk/qlasskit
Classifier: Programming Language :: Python
Classifier: Programming Language :: Python :: 3.9
Classifier: Programming Language :: Python :: 3.10
Classifier: Programming Language :: Python :: 3.11
Classifier: Programming Language :: Python :: 3.12
Classifier: Programming Language :: Python :: 3.13
Classifier: Development Status :: 5 - Production/Stable
Classifier: Topic :: Scientific/Engineering :: Physics
Classifier: Operating System :: OS Independent
Requires-Python: >=3.9.0
License-File: LICENSE
Requires-Dist: sympy==1.12
Provides-Extra: tweedledum
Requires-Dist: tweedledum==1.1.1; extra == "tweedledum"
Provides-Extra: bqm
Requires-Dist: pyqubo==1.0.5; extra == "bqm"
Dynamic: license-file
